equipment_cyg/__init__.py
equipment_cyg/controller/__init__.py
equipment_cyg/controller/controller.py
equipment_cyg/controller/enum_sece_data_type.py
equipment_cyg/controller/exception.py
equipment_cyg/external/inovance_tag_dll/InoTagAccess.dll
equipment_cyg/external/inovance_tag_dll/InoTagComCSharp.dll
equipment_cyg/external/inovance_tag_dll/PacTagCom.dll
equipment_cyg/external/inovance_tag_dll/RtosLib64.dll
equipment_cyg/external/inovance_tag_dll/Tag.dll
equipment_cyg/external/inovance_tag_dll/TagAccessCS.dll
equipment_cyg/product/__init__.py
equipment_cyg/product/ceribell/__init__.py
equipment_cyg/product/ceribell/ceribell.conf
equipment_cyg/product/ceribell/ceribell.py
equipment_cyg/product/ceribell/Ceribell_手册整理-20240821.xlsx
equipment_cyg/product/tong_fu_wei/__init__.py
equipment_cyg/product/tong_fu_wei/cyg_alarm.csv
equipment_cyg/product/tong_fu_wei/tong_fu_wei.conf
equipment_cyg/product/tong_fu_wei/tong_fu_wei.py
equipment_cyg/product/tong_fu_wei/通富微_手册整理-20240801.xlsx
equipment_cyg/product/zhong_che_yi_xing/__init__.py
equipment_cyg/product/zhong_che_yi_xing/cyg_alarm.csv
equipment_cyg/product/zhong_che_yi_xing/zhong_che_yi_xing.conf
equipment_cyg/product/zhong_che_yi_xing/zhong_che_yi_xing.py
equipment_cyg/product/zhong_che_yi_xing/中车宜兴手册整理-20240924.xlsx
equipment_cyg/product/zhong_che_zhu_zhou/__init__.py
equipment_cyg/product/zhong_che_zhu_zhou/zhong_che_zhu_zhou.conf
equipment_cyg/product/zhong_che_zhu_zhou/zhong_che_zhu_zhou.py
equipment_cyg/product/zhong_che_zhu_zhou/zhong_che_zhu_zhou_temp.conf
equipment_cyg/product/zhong_che_zhu_zhou/zhong_che_zhu_zhou_temp.py
equipment_cyg/product/zhong_che_zhu_zhou/中车株洲_手册整理-20240919更新.xlsx
equipment_cyg/utils/__init__.py
equipment_cyg/utils/airtable/__init__.py
equipment_cyg/utils/airtable/airtable.py
equipment_cyg/utils/plc/__init__.py
equipment_cyg/utils/plc/exception.py
equipment_cyg/utils/plc/plc_inovance.py
equipment_cyg/utils/plc/tag_communication.py
equipment_cyg/utils/plc/tag_type_enum.py
equipment_cyg-1.1.5.dist-info/METADATA
equipment_cyg-1.1.5.dist-info/WHEEL
equipment_cyg-1.1.5.dist-info/RECORD
