Metadata-Version: 2.1
Name: equipment_cyg
Version: 1.1.5
Summary: 
Home-page: https://github.com/ChangYuan-Semiconductor-Equipment/equipment_cyg.git
Author: WeiLiu
Author-email: 183074632@qq.com
Requires-Python: >=3.10,<3.13
Classifier: Programming Language :: Python :: 3
Classifier: Programming Language :: Python :: 3.10
Classifier: Programming Language :: Python :: 3.11
Classifier: Programming Language :: Python :: 3.12
Requires-Dist: black (>=24.8.0,<25.0.0)
Requires-Dist: cffi (>=1.17.0,<2.0.0)
Requires-Dist: flake8 (>=7.1.0,<8.0.0)
Requires-Dist: isort (>=5.13.2,<6.0.0)
Requires-Dist: modbus-tk (>=1.1.3,<2.0.0)
Requires-Dist: pillow (>=10.4.0,<11.0.0)
Requires-Dist: pyairtable (>=2.3.3,<3.0.0)
Requires-Dist: pylint (>=3.3.0,<4.0.0)
Requires-Dist: pymysql (>=1.1.1,<2.0.0)
Requires-Dist: pythonnet (==3.0.3)
Requires-Dist: secsgem_cyg (>=1.0.2,<2.0.0)
Requires-Dist: sqlalchemy (>=2.0.31,<3.0.0)
Requires-Dist: suds-community (>=1.2.0,<2.0.0)
Project-URL: Repository, https://github.com/ChangYuan-Semiconductor-Equipment/equipment_cyg.git
